iaar_tools/__init__.py
iaar_tools/__init__.pyi
iaar_tools/_better_exceptions.py
iaar_tools/_colorama.py
iaar_tools/_colorizer.py
iaar_tools/_ctime_functions.py
iaar_tools/_datetime.py
iaar_tools/_defaults.py
iaar_tools/_error_interceptor.py
iaar_tools/_file_sink.py
iaar_tools/_filters.py
iaar_tools/_get_frame.py
iaar_tools/_handler.py
iaar_tools/_locks_machinery.py
iaar_tools/_logger.py
iaar_tools/_recattrs.py
iaar_tools/_simple_sinks.py
iaar_tools/_string_parsers.py
iaar_tools/generate_mongo_ts.py
iaar_tools/iaarLog.py
iaar_tools/iaarLogger.py
iaar_tools/inner_ip.py
iaar_tools-1.0.0.dist-info/METADATA
iaar_tools-1.0.0.dist-info/WHEEL
iaar_tools-1.0.0.dist-info/top_level.txt
iaar_tools-1.0.0.dist-info/zip-safe
iaar_tools-1.0.0.dist-info/RECORD
